cli.py
pacrepo_cli-1.1.1.dist-info/METADATA
pacrepo_cli-1.1.1.dist-info/WHEEL
pacrepo_cli-1.1.1.dist-info/entry_points.txt
pacrepo_cli-1.1.1.dist-info/top_level.txt
pacrepo_cli-1.1.1.dist-info/RECORD
