Metadata-Version: 2.1
Name: pacrepo-cli
Version: 1.1.1
Summary: Quick Tool for managing user repos in pacman.conf
Home-page: https://github.com/jckimble/pacrepo-cli
Author: James C Kimble
Author-email: me@jckimble.com
License: ISC
Keywords: archlinux unofficial pacman pacman.conf user repo repository
Classifier: Programming Language :: Python :: 3
Requires-Dist: click
